[
    {
        "id": 17845439309873078,
        "created_at": 1667086788,
        "text": "minnn kalo dari smk bisa masuk uin gasii \ud83e\udd7apengen banget tapi harapan kecil kayanya",
        "owner": {
            "id": "7244209059",
            "is_verified": false,
            "profile_pic_url": "https://scontent-sin6-4.cdninstagram.com/v/t51.2885-19/353031521_557639686572193_3850532985698942218_n.jpg?stp=dst-jpg_s150x150&_nc_ht=scontent-sin6-4.cdninstagram.com&_nc_cat=101&_nc_ohc=4S4isPA850IAX-W_6iS&edm=AMrZAGUBAAAA&ccb=7-5&oh=00_AfDUIkGWhcMSZTySDlMcK_jvSK70LYyj5Gd-7OuoSPMsVw&oe=64DD415B&_nc_sid=17eaee",
            "username": "bilqislylaaa"
        },
        "likes_count": 0,
        "answers": []
    },
    {
        "id": 17945632100506863,
        "created_at": 1665555571,
        "text": "Ikut PPDB ditahun 2016, kalo gak cek cek instagram uin unofficial, grup2 di fb gak akan dapet info apapun. Syukurlah sekarang...",
        "owner": {
            "id": "4670119464",
            "is_verified": false,
            "profile_pic_url": "https://scontent-sin6-3.cdninstagram.com/v/t51.2885-19/357781416_780250606919008_7836000923389683265_n.jpg?stp=dst-jpg_s150x150&_nc_ht=scontent-sin6-3.cdninstagram.com&_nc_cat=104&_nc_ohc=CYPRwkJeSvIAX_O5gAy&edm=AMrZAGUBAAAA&ccb=7-5&oh=00_AfDCpWLF13Kbe53NfA9QDDVupnhGPpi2Ub492bUWIiVTNA&oe=64DCD428&_nc_sid=17eaee",
            "username": "hilmiatori"
        },
        "likes_count": 0,
        "answers": []
    },
    {
        "id": 17887654754718837,
        "created_at": 1665550760,
        "text": "\u2764\ufe0f\u2764\ufe0f",
        "owner": {
            "id": "54776323365",
            "is_verified": false,
            "profile_pic_url": "https://scontent-sin6-4.cdninstagram.com/v/t51.2885-19/297589100_3377126565892908_3608259975657184929_n.jpg?stp=dst-jpg_s150x150&_nc_ht=scontent-sin6-4.cdninstagram.com&_nc_cat=100&_nc_ohc=-JHvYeSFY2UAX_EEH9z&edm=AMrZAGUBAAAA&ccb=7-5&oh=00_AfBSbFGZu2mkHOq5aBFcr6BFHIENuwko107K2o3bkKtrIA&oe=64DD5851&_nc_sid=17eaee",
            "username": "agung.sp1"
        },
        "likes_count": 0,
        "answers": []
    }
]