[
    {
        "id": 17907538172612139,
        "created_at": 1670670440,
        "text": "Yuk siapin bucketnya \ud83d\ude0d\ud83d\ude0d",
        "owner": {
            "id": "47372576149",
            "is_verified": false,
            "profile_pic_url": "https://scontent-sin6-3.cdninstagram.com/v/t51.2885-19/318834128_668274828325162_8065282153881133626_n.jpg?stp=dst-jpg_s150x150&_nc_ht=scontent-sin6-3.cdninstagram.com&_nc_cat=110&_nc_ohc=2e7zUx53iM4AX-SUtFU&edm=AMrZAGUBAAAA&ccb=7-5&oh=00_AfCCNVK_Ue-uITsscJTO1vV3sbsLiYOv7I9IfCI35Ym6DA&oe=64DD24AC&_nc_sid=17eaee",
            "username": "giftstore.byme"
        },
        "likes_count": 0,
        "answers": []
    },
    {
        "id": 18201567625173052,
        "created_at": 1670644223,
        "text": "S2 d UIN apa z min",
        "owner": {
            "id": "31630429838",
            "is_verified": false,
            "profile_pic_url": "https://scontent-sin6-2.cdninstagram.com/v/t51.2885-19/271242580_304145324967542_6187943515249676152_n.jpg?stp=dst-jpg_s150x150&_nc_ht=scontent-sin6-2.cdninstagram.com&_nc_cat=102&_nc_ohc=NXGlcJvJqqIAX_o-aMt&edm=AMrZAGUBAAAA&ccb=7-5&oh=00_AfCiJd06AWhYTj1F3PQWOkXyJUp79dGN5cWTAFvSejjGEg&oe=64DE94E6&_nc_sid=17eaee",
            "username": "ummahkoe"
        },
        "likes_count": 0,
        "answers": []
    },
    {
        "id": 18332610013025956,
        "created_at": 1670589503,
        "text": "Siap mengantarkan kakak kakak kami \u2728\ud83d\udcaa",
        "owner": {
            "id": "1499055922",
            "is_verified": false,
            "profile_pic_url": "https://scontent-sin6-3.cdninstagram.com/v/t51.2885-19/43762817_595243330909348_2717406042739703808_n.jpg?stp=dst-jpg_s150x150&_nc_ht=scontent-sin6-3.cdninstagram.com&_nc_cat=104&_nc_ohc=DTJFoTPq3r0AX_LrQjW&edm=AMrZAGUBAAAA&ccb=7-5&oh=00_AfDWtoUAR2RkTwx6QcuElFD0Q9vlaxcQG1Lw38fo8fwWJA&oe=64DD8E17&_nc_sid=17eaee",
            "username": "pramukauinsgd"
        },
        "likes_count": 1,
        "answers": []
    },
    {
        "id": 18196313968213265,
        "created_at": 1670581757,
        "text": "Oww Masya Allah Barakallah geuliss @mentarifuzi",
        "owner": {
            "id": "2100050810",
            "is_verified": false,
            "profile_pic_url": "https://scontent-sin6-1.cdninstagram.com/v/t51.2885-19/325521055_863916538057207_4833727400886881791_n.jpg?stp=dst-jpg_s150x150&_nc_ht=scontent-sin6-1.cdninstagram.com&_nc_cat=107&_nc_ohc=wI0QSKMje84AX-I9Lnq&edm=AMrZAGUBAAAA&ccb=7-5&oh=00_AfBJaQyrZaauR6mORfy1vR19MHNa6eBhSdg5xjkwplJ01A&oe=64DD1C81&_nc_sid=17eaee",
            "username": "depi_hasanah1"
        },
        "likes_count": 0,
        "answers": [
            {
                "id": 17938834193352521,
                "created_at": 1670583950,
                "text": "@depi_hasanah1 masyaAllah tabarakallah htrnuhun panutanku..",
                "owner": {
                    "id": "609433990",
                    "is_verified": false,
                    "profile_pic_url": "https://scontent-sin6-2.cdninstagram.com/v/t51.2885-19/336503759_194521559941877_8694722351000520584_n.jpg?stp=dst-jpg_s150x150&_nc_ht=scontent-sin6-2.cdninstagram.com&_nc_cat=105&_nc_ohc=NkdDCdaCnhUAX9ig76W&edm=AMrZAGUBAAAA&ccb=7-5&oh=00_AfC5VZrL20wzNFFkCr_6KJ32gV9jZzW-Fxf8zqt1thVs3g&oe=64DE01FF&_nc_sid=17eaee",
                    "username": "mentarifuzi"
                },
                "likes_count": 0
            }
        ]
    },
    {
        "id": 17955801767201655,
        "created_at": 1670560591,
        "text": "\ud83d\udd25",
        "owner": {
            "id": "46382572588",
            "is_verified": false,
            "profile_pic_url": "https://scontent-sin6-4.cdninstagram.com/v/t51.2885-19/292049810_1128441401216631_9195548136255187596_n.jpg?stp=dst-jpg_s150x150&_nc_ht=scontent-sin6-4.cdninstagram.com&_nc_cat=103&_nc_ohc=bM5PmWNvCikAX8OKStq&edm=AMrZAGUBAAAA&ccb=7-5&oh=00_AfC3rY_ojfPIx7pdrxy_1TLmLMOxLo_8Q4a0wJzCbbuwtQ&oe=64DE4810&_nc_sid=17eaee",
            "username": "dinayvalentineeee"
        },
        "likes_count": 0,
        "answers": []
    },
    {
        "id": 17861777837801705,
        "created_at": 1670545488,
        "text": "yg wisuda online cant relate",
        "owner": {
            "id": "5800749101",
            "is_verified": false,
            "profile_pic_url": "https://scontent-sin6-2.cdninstagram.com/v/t51.2885-19/279163862_364288352409969_5220990561964835828_n.jpg?stp=dst-jpg_s150x150&_nc_ht=scontent-sin6-2.cdninstagram.com&_nc_cat=109&_nc_ohc=KWOAG8UNeWIAX_e-5Lm&edm=AMrZAGUBAAAA&ccb=7-5&oh=00_AfCSwuBL3rkG85ykHGhQKEXvvkMoR3eq6xUbcdoVPC5mBA&oe=64DD5907&_nc_sid=17eaee",
            "username": "dnjniptr"
        },
        "likes_count": 0,
        "answers": []
    },
    {
        "id": 17847741842894422,
        "created_at": 1670533073,
        "text": "@ka_risss ada siapa tuuuuh\ud83d\ude05",
        "owner": {
            "id": "8964621214",
            "is_verified": false,
            "profile_pic_url": "https://scontent-sin6-4.cdninstagram.com/v/t51.2885-19/308051203_657224978936545_4089984432594228832_n.jpg?stp=dst-jpg_s150x150&_nc_ht=scontent-sin6-4.cdninstagram.com&_nc_cat=101&_nc_ohc=gUqCUvHStrQAX_XneeV&edm=AMrZAGUBAAAA&ccb=7-5&oh=00_AfAy5ASfXQHRdvdeMDSoT-HPA-HOvzx_N3N7mzn8Y7sOrQ&oe=64DCA8DB&_nc_sid=17eaee",
            "username": "jng.hermawan"
        },
        "likes_count": 1,
        "answers": [
            {
                "id": 17970421750853964,
                "created_at": 1670533796,
                "text": "@jng.hermawan ehehe\ud83d\ude02",
                "owner": {
                    "id": "1423843196",
                    "is_verified": false,
                    "profile_pic_url": "https://scontent-sin6-3.cdninstagram.com/v/t51.2885-19/117075905_339046800441418_5789945660542026207_n.jpg?stp=dst-jpg_s150x150&_nc_ht=scontent-sin6-3.cdninstagram.com&_nc_cat=110&_nc_ohc=xxGcM4f7SfkAX-TWmrV&edm=AMrZAGUBAAAA&ccb=7-5&oh=00_AfBej0J_8kq0jd7dn3e0N5C6RF33sIyOEzPsDQ4hPVlICA&oe=64DCECC0&_nc_sid=17eaee",
                    "username": "ka_risss"
                },
                "likes_count": 0
            }
        ]
    },
    {
        "id": 17870679782801589,
        "created_at": 1670522456,
        "text": "Spill editor nya min",
        "owner": {
            "id": "7932957153",
            "is_verified": false,
            "profile_pic_url": "https://scontent-sin6-3.cdninstagram.com/v/t51.2885-19/346033761_3293357800915780_1474905343471575943_n.jpg?stp=dst-jpg_s150x150&_nc_ht=scontent-sin6-3.cdninstagram.com&_nc_cat=104&_nc_ohc=RlYyT3yGOBgAX-PjPzC&edm=AMrZAGUBAAAA&ccb=7-5&oh=00_AfDvZGKqDaHTAmQmEHlsG7BVHnsKiJ9QuiaGE6ThbZIZLw&oe=64DD1725&_nc_sid=17eaee",
            "username": "way.rul"
        },
        "likes_count": 0,
        "answers": []
    },
    {
        "id": 17956492181323967,
        "created_at": 1670507040,
        "text": "Si \"Mentari\" esok kian bersinarrrrr\ud83d\udc4f\ud83d\udc4f\ud83d\udc4f\ud83c\udffb\ud83d\udc4f\ud83d\ude0d",
        "owner": {
            "id": "6932519121",
            "is_verified": false,
            "profile_pic_url": "https://scontent-sin6-3.cdninstagram.com/v/t51.2885-19/355061563_3497395110551574_5503961332124522893_n.jpg?stp=dst-jpg_s150x150&_nc_ht=scontent-sin6-3.cdninstagram.com&_nc_cat=106&_nc_ohc=_2wzA_Zxk9YAX_Xkp5p&edm=AMrZAGUBAAAA&ccb=7-5&oh=00_AfAfFrbHPFiUKbKDHDtCm6zbKFH54Hy2u5IjaA8h6rkTUw&oe=64DD9940&_nc_sid=17eaee",
            "username": "novi.ansyah.169"
        },
        "likes_count": 0,
        "answers": []
    },
    {
        "id": 17977983664849529,
        "created_at": 1670506081,
        "text": "\u2764\ufe0f",
        "owner": {
            "id": "44543686590",
            "is_verified": false,
            "profile_pic_url": "https://scontent-sin6-4.cdninstagram.com/v/t51.2885-19/362942145_831628101805393_7924100472030416684_n.jpg?stp=dst-jpg_s150x150&_nc_ht=scontent-sin6-4.cdninstagram.com&_nc_cat=101&_nc_ohc=0Bo_ixUIAfsAX-eBADg&edm=AMrZAGUBAAAA&ccb=7-5&oh=00_AfAym2n8LhK6dQQ_dovKCBiRgHrqYAow0xBuYNpewWS4OA&oe=64DDEAC6&_nc_sid=17eaee",
            "username": "dhonrm3"
        },
        "likes_count": 0,
        "answers": []
    },
    {
        "id": 17968232495052281,
        "created_at": 1670505125,
        "text": "Alhamdulillah \u2764\ufe0f\u2764\ufe0f\u2764\ufe0f",
        "owner": {
            "id": "8159869713",
            "is_verified": false,
            "profile_pic_url": "https://scontent-sin6-4.cdninstagram.com/v/t51.2885-19/227256720_246075547356912_1063496809987115290_n.jpg?stp=dst-jpg_s150x150&_nc_ht=scontent-sin6-4.cdninstagram.com&_nc_cat=100&_nc_ohc=julEWwFCKBsAX8JhD9y&edm=AMrZAGUBAAAA&ccb=7-5&oh=00_AfC1HXe0CK9Bg2zHfgAOmmbIaJtIhur3D6teAB_MeJoDPQ&oe=64DD2F7C&_nc_sid=17eaee",
            "username": "aiza.rachmatcollections"
        },
        "likes_count": 1,
        "answers": []
    },
    {
        "id": 18258095836143411,
        "created_at": 1670500140,
        "text": "Pengen wisuda tpi munaqasyahnya belumm hhu",
        "owner": {
            "id": "3685913853",
            "is_verified": false,
            "profile_pic_url": "https://scontent-sin6-4.cdninstagram.com/v/t51.2885-19/366116533_998679167995717_2582621263181830065_n.jpg?stp=dst-jpg_s150x150&_nc_ht=scontent-sin6-4.cdninstagram.com&_nc_cat=101&_nc_ohc=jJ5OcHieqMIAX_TSc6S&edm=AMrZAGUBAAAA&ccb=7-5&oh=00_AfDRGNvcg2VJwTJjV2ZETLPalWYjz5D8NOXRRJakN_bNFw&oe=64DE818D&_nc_sid=17eaee",
            "username": "aamisbah_"
        },
        "likes_count": 1,
        "answers": []
    },
    {
        "id": 17851092734879811,
        "created_at": 1670499134,
        "text": "\ud83d\udc68\u200d\ud83c\udfa4",
        "owner": {
            "id": "3185685321",
            "is_verified": false,
            "profile_pic_url": "https://scontent-sin6-4.cdninstagram.com/v/t51.2885-19/356401966_144174125308755_7051194424865468204_n.jpg?stp=dst-jpg_s150x150&_nc_ht=scontent-sin6-4.cdninstagram.com&_nc_cat=103&_nc_ohc=xj_KHFDOSzAAX9erAI2&edm=AMrZAGUBAAAA&ccb=7-5&oh=00_AfCW5oO_Jd4MRGwv5uiWTzcVXfsKVrn75BZ3LOCJv3o_lA&oe=64DDE58A&_nc_sid=17eaee",
            "username": "dah_sang_pena"
        },
        "likes_count": 1,
        "answers": []
    },
    {
        "id": 18054500713365417,
        "created_at": 1670499071,
        "text": "Met maceeet",
        "owner": {
            "id": "1621810136",
            "is_verified": false,
            "profile_pic_url": "https://scontent-sin6-3.cdninstagram.com/v/t51.2885-19/351439234_1354305468466264_3829445927078365009_n.jpg?stp=dst-jpg_s150x150&_nc_ht=scontent-sin6-3.cdninstagram.com&_nc_cat=104&_nc_ohc=SJZKJeORYA8AX-nVDhf&edm=AMrZAGUBAAAA&ccb=7-5&oh=00_AfD6F1xRjj_GXLS0f2edzInL2ae7TCdMroG_alqb1og8rw&oe=64DE6F1E&_nc_sid=17eaee",
            "username": "trnirahmaa_"
        },
        "likes_count": 1,
        "answers": []
    },
    {
        "id": 17937319895528502,
        "created_at": 1670498291,
        "text": "UIN tunggu gue tahun depan yakkkkk",
        "owner": {
            "id": "33542924398",
            "is_verified": false,
            "profile_pic_url": "https://scontent-sin6-1.cdninstagram.com/v/t51.2885-19/363519149_299480639237495_1437770037251863185_n.jpg?stp=dst-jpg_s150x150&_nc_ht=scontent-sin6-1.cdninstagram.com&_nc_cat=111&_nc_ohc=yTT80d2nkLcAX-l6kwn&edm=AMrZAGUBAAAA&ccb=7-5&oh=00_AfBe_6RVAV8fZCulE1fR1UpqFib5764wZP3MQ3MqEzSaxQ&oe=64DDA738&_nc_sid=17eaee",
            "username": "teguhfajarrn"
        },
        "likes_count": 1,
        "answers": []
    },
    {
        "id": 17955774155245143,
        "created_at": 1670498018,
        "text": "@frisyeuwjywti kapan euyy\ud83d\ude02",
        "owner": {
            "id": "2089420805",
            "is_verified": false,
            "profile_pic_url": "https://scontent-sin6-1.cdninstagram.com/v/t51.2885-19/275504106_626528595113503_4913182208213200087_n.jpg?stp=dst-jpg_s150x150&_nc_ht=scontent-sin6-1.cdninstagram.com&_nc_cat=107&_nc_ohc=BVQ9emBv6ygAX_x8Des&edm=AMrZAGUBAAAA&ccb=7-5&oh=00_AfBUsH_0AR2SkuGcSSHzSeUe_z48HGUQuTLPWvnHwzLHAQ&oe=64DDC0D7&_nc_sid=17eaee",
            "username": "anggi_aninditiya"
        },
        "likes_count": 1,
        "answers": []
    },
    {
        "id": 17934006311463611,
        "created_at": 1670497538,
        "text": "Tim maret mah senyum aja",
        "owner": {
            "id": "4481574273",
            "is_verified": false,
            "profile_pic_url": "https://scontent-sin6-4.cdninstagram.com/v/t51.2885-19/325695896_182573134378561_3950527425925457870_n.jpg?stp=dst-jpg_s150x150&_nc_ht=scontent-sin6-4.cdninstagram.com&_nc_cat=101&_nc_ohc=HnendLEbRXUAX8GcrFW&edm=AMrZAGUBAAAA&ccb=7-5&oh=00_AfBXMf8JlzaetI0bTHtSEQK3t2MUh4GkmUNH5C8UBNGywA&oe=64DDAE7F&_nc_sid=17eaee",
            "username": "mrizalzlhm_01"
        },
        "likes_count": 4,
        "answers": [
            {
                "id": 17988588040640777,
                "created_at": 1670498832,
                "text": "@mrizalzlhm_01 hahhhh katanya mau brg",
                "owner": {
                    "id": "639037233",
                    "is_verified": false,
                    "profile_pic_url": "https://scontent-sin6-1.cdninstagram.com/v/t51.2885-19/331099973_230986395947195_1107958457437103259_n.jpg?stp=dst-jpg_s150x150&_nc_ht=scontent-sin6-1.cdninstagram.com&_nc_cat=111&_nc_ohc=ozAnbgwXl6AAX8PWF-G&edm=AMrZAGUBAAAA&ccb=7-5&oh=00_AfB-7fQiJBKoHZJyQE7LL8BcovTtLjI1hwzRCCglET59EQ&oe=64DDA550&_nc_sid=17eaee",
                    "username": "ikaagstnn"
                },
                "likes_count": 0
            },
            {
                "id": 17949002672373509,
                "created_at": 1670562169,
                "text": "@ikaagstnn jadinya maret akuu",
                "owner": {
                    "id": "4481574273",
                    "is_verified": false,
                    "profile_pic_url": "https://scontent-sin6-4.cdninstagram.com/v/t51.2885-19/325695896_182573134378561_3950527425925457870_n.jpg?stp=dst-jpg_s150x150&_nc_ht=scontent-sin6-4.cdninstagram.com&_nc_cat=101&_nc_ohc=HnendLEbRXUAX8GcrFW&edm=AMrZAGUBAAAA&ccb=7-5&oh=00_AfBXMf8JlzaetI0bTHtSEQK3t2MUh4GkmUNH5C8UBNGywA&oe=64DDAE7F&_nc_sid=17eaee",
                    "username": "mrizalzlhm_01"
                },
                "likes_count": 0
            }
        ]
    },
    {
        "id": 18097363117307639,
        "created_at": 1670497349,
        "text": "Wiii \ud83d\udc4f\ud83d\udc4f\ud83d\udc4f\ud83d\udd25\ud83d\udd25\ud83d\udd25",
        "owner": {
            "id": "57143220294",
            "is_verified": false,
            "profile_pic_url": "https://scontent-sin6-3.cdninstagram.com/v/t51.2885-19/318204157_1576517129452498_1167118221401837133_n.jpg?stp=dst-jpg_s150x150&_nc_ht=scontent-sin6-3.cdninstagram.com&_nc_cat=110&_nc_ohc=OEGijeQ4AQkAX--E8ze&edm=AMrZAGUBAAAA&ccb=7-5&oh=00_AfBlKdvEJ1I-_VbpNeTaKm1aTsh-dDNSpinL608oq2u80g&oe=64DD4B53&_nc_sid=17eaee",
            "username": "uinconfessions"
        },
        "likes_count": 1,
        "answers": []
    },
    {
        "id": 17958988982319468,
        "created_at": 1670496296,
        "text": "Menggebu pengen lgi wisuda, kangen kampus dan isi'y",
        "owner": {
            "id": "1494878274",
            "is_verified": false,
            "profile_pic_url": "https://scontent-sin6-4.cdninstagram.com/v/t51.2885-19/321822833_130514736562452_5646361174529312505_n.jpg?stp=dst-jpg_s150x150&_nc_ht=scontent-sin6-4.cdninstagram.com&_nc_cat=100&_nc_ohc=WTSl3po7UmMAX-MnKLO&edm=AMrZAGUBAAAA&ccb=7-5&oh=00_AfApOG0nF0HRXEJCiMyDPPQDBO3MFnyxxlin4fIeGdi8_Q&oe=64DD1833&_nc_sid=17eaee",
            "username": "cmpk4693"
        },
        "likes_count": 1,
        "answers": []
    },
    {
        "id": 17965837531913637,
        "created_at": 1670496101,
        "text": "Mantap",
        "owner": {
            "id": "1386431212",
            "is_verified": false,
            "profile_pic_url": "https://scontent-sin6-4.cdninstagram.com/v/t51.2885-19/365141162_6347829365271517_5850211999215096796_n.jpg?stp=dst-jpg_s150x150&_nc_ht=scontent-sin6-4.cdninstagram.com&_nc_cat=101&_nc_ohc=0VAZxeZ4ZTcAX8pHyvV&edm=AMrZAGUBAAAA&ccb=7-5&oh=00_AfCd2ExcvsT5earlABGPey2e2CQ7uLm4lgj3k9sdPjPjXw&oe=64DE030B&_nc_sid=17eaee",
            "username": "usmanalkafi"
        },
        "likes_count": 1,
        "answers": []
    },
    {
        "id": 18064565359342645,
        "created_at": 1670496083,
        "text": "\ud83d\udd25\ud83d\udd25\ud83d\udd25\ud83d\udd25\ud83d\udd25\ud83d\udd25",
        "owner": {
            "id": "8273260305",
            "is_verified": false,
            "profile_pic_url": "https://scontent-sin6-2.cdninstagram.com/v/t51.2885-19/347901318_565577282436621_3778653816422892903_n.jpg?stp=dst-jpg_s150x150&_nc_ht=scontent-sin6-2.cdninstagram.com&_nc_cat=109&_nc_ohc=MnjLY0K7V-sAX-p8fl9&edm=AMrZAGUBAAAA&ccb=7-5&oh=00_AfCYhIWBPOqcpZ5_bTWAvZcHbPs1Menwp4nPtfRFMZPe0Q&oe=64DE0FD2&_nc_sid=17eaee",
            "username": "ocktadila"
        },
        "likes_count": 1,
        "answers": []
    },
    {
        "id": 17931372863599343,
        "created_at": 1670495843,
        "text": "mirip para hokage lg jalan \ud83d\udc4d\ud83c\udffb",
        "owner": {
            "id": "1647941805",
            "is_verified": false,
            "profile_pic_url": "https://scontent-sin6-3.cdninstagram.com/v/t51.2885-19/243188871_590319098990860_3537546069383645451_n.jpg?stp=dst-jpg_s150x150&_nc_ht=scontent-sin6-3.cdninstagram.com&_nc_cat=104&_nc_ohc=gW0KRO-rSu4AX-x-bnK&edm=AMrZAGUBAAAA&ccb=7-5&oh=00_AfDhfd57wM2wcBPgipNU7hM9k-ViQyotOcEmsDtsFJez7g&oe=64DCC472&_nc_sid=17eaee",
            "username": "deden_muhsin"
        },
        "likes_count": 1,
        "answers": []
    },
    {
        "id": 17986836448665344,
        "created_at": 1670495750,
        "text": "@almaula_dina216 meuniii gayaaa kitu eceu\u2764\ufe0f",
        "owner": {
            "id": "1276961338",
            "is_verified": false,
            "profile_pic_url": "https://scontent-sin6-3.cdninstagram.com/v/t51.2885-19/350079696_1946670129020284_8171234915199644442_n.jpg?stp=dst-jpg_s150x150&_nc_ht=scontent-sin6-3.cdninstagram.com&_nc_cat=104&_nc_ohc=90ZE6Z_LzYoAX9sixI2&edm=AMrZAGUBAAAA&ccb=7-5&oh=00_AfAEP5x5BZ3Dr2vY1un8IvkvgjHOfpqtFoXUYPsTgsficQ&oe=64DE4EAE&_nc_sid=17eaee",
            "username": "ameliaiaw"
        },
        "likes_count": 3,
        "answers": []
    },
    {
        "id": 17930870249554544,
        "created_at": 1670495418,
        "text": "Bismillah tahun depan \ud83d\udd25\ud83d\udd25\ud83d\udd25",
        "owner": {
            "id": "50795551562",
            "is_verified": false,
            "profile_pic_url": "https://scontent-sin6-3.cdninstagram.com/v/t51.2885-19/359960494_2038994696434794_2059018237417399100_n.jpg?stp=dst-jpg_s150x150&_nc_ht=scontent-sin6-3.cdninstagram.com&_nc_cat=106&_nc_ohc=M71ZNNMh6lkAX-5EEy5&edm=AMrZAGUBAAAA&ccb=7-5&oh=00_AfBy-XC-nZamtwrgLlGifONMAVQq5FXb84EifY0LSpRhgQ&oe=64DD24A6&_nc_sid=17eaee",
            "username": "nuryadiriko"
        },
        "likes_count": 2,
        "answers": []
    },
    {
        "id": 18028011739432103,
        "created_at": 1670495325,
        "text": "Cihuy euforia nya dah kerasa\ud83d\udc83\ud83c\udffb @hendaodod @elsarinjani181 @ikaagstnn @cucu_ns @eriilatifatzhra @bertipuspa",
        "owner": {
            "id": "2280329922",
            "is_verified": false,
            "profile_pic_url": "https://scontent-sin6-3.cdninstagram.com/v/t51.2885-19/352193626_165792906309826_7907734879834846670_n.jpg?stp=dst-jpg_s150x150&_nc_ht=scontent-sin6-3.cdninstagram.com&_nc_cat=110&_nc_ohc=XBKOkrZ77yAAX8QW46R&edm=AMrZAGUBAAAA&ccb=7-5&oh=00_AfDBL3XqIhio94X4yhK_PpGRLGfwx4SQdWQDDpMZW9oj6w&oe=64DE8FC0&_nc_sid=17eaee",
            "username": "bessarany"
        },
        "likes_count": 2,
        "answers": [
            {
                "id": 17871010262801401,
                "created_at": 1670498857,
                "text": "@bessarany aaaa terharu brg",
                "owner": {
                    "id": "639037233",
                    "is_verified": false,
                    "profile_pic_url": "https://scontent-sin6-1.cdninstagram.com/v/t51.2885-19/331099973_230986395947195_1107958457437103259_n.jpg?stp=dst-jpg_s150x150&_nc_ht=scontent-sin6-1.cdninstagram.com&_nc_cat=111&_nc_ohc=ozAnbgwXl6AAX8PWF-G&edm=AMrZAGUBAAAA&ccb=7-5&oh=00_AfB-7fQiJBKoHZJyQE7LL8BcovTtLjI1hwzRCCglET59EQ&oe=64DDA550&_nc_sid=17eaee",
                    "username": "ikaagstnn"
                },
                "likes_count": 0
            }
        ]
    },
    {
        "id": 17934538343587585,
        "created_at": 1670494649,
        "text": "Wihhh ada @ka_risss keren banget huhuhu bangga banget\ud83e\udd17\ud83e\udd7a",
        "owner": {
            "id": "2207082530",
            "is_verified": false,
            "profile_pic_url": "https://scontent-sin6-2.cdninstagram.com/v/t51.2885-19/355061569_723676659556341_6614311984424825692_n.jpg?stp=dst-jpg_s150x150&_nc_ht=scontent-sin6-2.cdninstagram.com&_nc_cat=109&_nc_ohc=7KbrBfeFvzsAX-pWV2i&edm=AMrZAGUBAAAA&ccb=7-5&oh=00_AfDdoTQDKGDh4No6-qcqPecLBUlQi3S9dmnqK97B9-hKtg&oe=64DE0712&_nc_sid=17eaee",
            "username": "wrdhindah_"
        },
        "likes_count": 2,
        "answers": [
            {
                "id": 17868718322812451,
                "created_at": 1670495321,
                "text": "@wrdhindah_ ehehe thank u indahh\ud83d\ude0d",
                "owner": {
                    "id": "1423843196",
                    "is_verified": false,
                    "profile_pic_url": "https://scontent-sin6-3.cdninstagram.com/v/t51.2885-19/117075905_339046800441418_5789945660542026207_n.jpg?stp=dst-jpg_s150x150&_nc_ht=scontent-sin6-3.cdninstagram.com&_nc_cat=110&_nc_ohc=xxGcM4f7SfkAX-TWmrV&edm=AMrZAGUBAAAA&ccb=7-5&oh=00_AfBej0J_8kq0jd7dn3e0N5C6RF33sIyOEzPsDQ4hPVlICA&oe=64DCECC0&_nc_sid=17eaee",
                    "username": "ka_risss"
                },
                "likes_count": 2
            }
        ]
    },
    {
        "id": 17960006993169871,
        "created_at": 1670494414,
        "text": "\ud83d\ude0d\ud83d\ude0d\ud83d\ude0d",
        "owner": {
            "id": "50656371797",
            "is_verified": false,
            "profile_pic_url": "https://scontent-sin6-4.cdninstagram.com/v/t51.2885-19/296088325_884376032953357_1596902333605253742_n.jpg?stp=dst-jpg_s150x150&_nc_ht=scontent-sin6-4.cdninstagram.com&_nc_cat=101&_nc_ohc=0h5KOheELGcAX8J7nC9&edm=AMrZAGUBAAAA&ccb=7-5&oh=00_AfCxgRheo1SS0pkewK42iXaDb5_AcK6Bfe8MPg3LrhXgIQ&oe=64DD3154&_nc_sid=17eaee",
            "username": "azaysee_bouquet_bdg"
        },
        "likes_count": 1,
        "answers": []
    },
    {
        "id": 18331580098014753,
        "created_at": 1670494289,
        "text": "Yg wisudanya minggu toganya bisa d ambil kapan min?",
        "owner": {
            "id": "48487070100",
            "is_verified": false,
            "profile_pic_url": "https://scontent-sin6-2.cdninstagram.com/v/t51.2885-19/201360939_2935535563352073_668574197116340470_n.jpg?stp=dst-jpg_s150x150&_nc_ht=scontent-sin6-2.cdninstagram.com&_nc_cat=109&_nc_ohc=ZaCT6FC6VQUAX9MXAiE&edm=AMrZAGUBAAAA&ccb=7-5&oh=00_AfBVyH_Tu0HKPHNk3XhL8xslrDjpA_rgvQubij31IALslw&oe=64DD00EF&_nc_sid=17eaee",
            "username": "coolo.ka"
        },
        "likes_count": 1,
        "answers": [
            {
                "id": 17936392706588716,
                "created_at": 1670497401,
                "text": "@coolo.ka izin jawab ka kalau tarbiyah dari kemarin juga udh bisa diambil",
                "owner": {
                    "id": "1551518331",
                    "is_verified": false,
                    "profile_pic_url": "https://scontent-sin6-2.cdninstagram.com/v/t51.2885-19/358516104_286805320423737_3090381814651115767_n.jpg?stp=dst-jpg_s150x150&_nc_ht=scontent-sin6-2.cdninstagram.com&_nc_cat=109&_nc_ohc=wfj6FLFmw_0AX9Iw-9s&edm=AMrZAGUBAAAA&ccb=7-5&oh=00_AfCj2ntDv7K6ofq3xiyqDiWs1FoEKY4-pGBUTkywIjZPXw&oe=64DD210F&_nc_sid=17eaee",
                    "username": "nadaalyautari"
                },
                "likes_count": 0
            },
            {
                "id": 17931448448603409,
                "created_at": 1670505228,
                "text": "@diahsultonah TU",
                "owner": {
                    "id": "1551518331",
                    "is_verified": false,
                    "profile_pic_url": "https://scontent-sin6-2.cdninstagram.com/v/t51.2885-19/358516104_286805320423737_3090381814651115767_n.jpg?stp=dst-jpg_s150x150&_nc_ht=scontent-sin6-2.cdninstagram.com&_nc_cat=109&_nc_ohc=wfj6FLFmw_0AX9Iw-9s&edm=AMrZAGUBAAAA&ccb=7-5&oh=00_AfCj2ntDv7K6ofq3xiyqDiWs1FoEKY4-pGBUTkywIjZPXw&oe=64DD210F&_nc_sid=17eaee",
                    "username": "nadaalyautari"
                },
                "likes_count": 0
            },
            {
                "id": 17889717626742400,
                "created_at": 1670504366,
                "text": "@nadaalyautari ngambilnya dman ak",
                "owner": {
                    "id": "2223821361",
                    "is_verified": false,
                    "profile_pic_url": "https://scontent-sin6-3.cdninstagram.com/v/t51.2885-19/319668572_174564591851668_4329440485414149749_n.jpg?stp=dst-jpg_s150x150&_nc_ht=scontent-sin6-3.cdninstagram.com&_nc_cat=104&_nc_ohc=mVTs0oAIdBkAX9Uisro&edm=AMrZAGUBAAAA&ccb=7-5&oh=00_AfCRLaGx9J6fkd7spaWudP_0CA2h93x6gBWEkgTsCGAOgg&oe=64DE1232&_nc_sid=17eaee",
                    "username": "diahsultonah"
                },
                "likes_count": 0
            }
        ]
    },
    {
        "id": 17980862239811136,
        "created_at": 1670494200,
        "text": "Cieee @mentarifuzi wisudaaaa",
        "owner": {
            "id": "1106867927",
            "is_verified": false,
            "profile_pic_url": "https://scontent-sin6-2.cdninstagram.com/v/t51.2885-19/310795035_499094205399056_865770509009189912_n.jpg?stp=dst-jpg_s150x150&_nc_ht=scontent-sin6-2.cdninstagram.com&_nc_cat=108&_nc_ohc=XwXoR4-u-YAAX_qHSF-&edm=AMrZAGUBAAAA&ccb=7-5&oh=00_AfCa4Sc4g4C_STfGsMFfJo9Ymhdwj7YEE0x-atSwxSFxag&oe=64DE835F&_nc_sid=17eaee",
            "username": "putridiesy"
        },
        "likes_count": 1,
        "answers": [
            {
                "id": 18269224177102027,
                "created_at": 1670506585,
                "text": "@putridiesy aduduhhhh panutanku jd malueee hihi\ud83d\ude0d\ud83d\ude0d\ud83d\ude0d",
                "owner": {
                    "id": "609433990",
                    "is_verified": false,
                    "profile_pic_url": "https://scontent-sin6-2.cdninstagram.com/v/t51.2885-19/336503759_194521559941877_8694722351000520584_n.jpg?stp=dst-jpg_s150x150&_nc_ht=scontent-sin6-2.cdninstagram.com&_nc_cat=105&_nc_ohc=NkdDCdaCnhUAX9ig76W&edm=AMrZAGUBAAAA&ccb=7-5&oh=00_AfC5VZrL20wzNFFkCr_6KJ32gV9jZzW-Fxf8zqt1thVs3g&oe=64DE01FF&_nc_sid=17eaee",
                    "username": "mentarifuzi"
                },
                "likes_count": 0
            }
        ]
    },
    {
        "id": 17880171098778001,
        "created_at": 1670493981,
        "text": "\ud83d\ude0d\ud83d\ude0d\ud83d\ude0d",
        "owner": {
            "id": "1657106052",
            "is_verified": false,
            "profile_pic_url": "https://scontent-sin6-3.cdninstagram.com/v/t51.2885-19/334528662_748963793276134_5269669518022768557_n.jpg?stp=dst-jpg_s150x150&_nc_ht=scontent-sin6-3.cdninstagram.com&_nc_cat=110&_nc_ohc=Yqz05q8Sco8AX-igEd9&edm=AMrZAGUBAAAA&ccb=7-5&oh=00_AfCRwovS19GvNJvN0tzr8n6wzRlaiSjhKxCcBvqNTCJixg&oe=64DD3F3B&_nc_sid=17eaee",
            "username": "silfiahadiana"
        },
        "likes_count": 2,
        "answers": [
            {
                "id": 18064261687353380,
                "created_at": 1670500977,
                "text": "@silfiahadiana barakallah semoga ilmunya bermanfaat.. bumil keren,, eh sekarang udah busui \ud83d\ude0d\ud83d\ude0d\ud83d\ude0d\ud83d\udd25\ud83d\udd25\ud83d\udd25",
                "owner": {
                    "id": "2088277025",
                    "is_verified": false,
                    "profile_pic_url": "https://scontent-sin6-3.cdninstagram.com/v/t51.2885-19/35532899_2185238595110032_3527583985985126400_n.jpg?stp=dst-jpg_s150x150&_nc_ht=scontent-sin6-3.cdninstagram.com&_nc_cat=104&_nc_ohc=6cFQEko6APsAX8Bo-wv&edm=AMrZAGUBAAAA&ccb=7-5&oh=00_AfDXi_OlVCBeoDFeTuRK63J90UBRFn-1_teo0f2x-EZjoA&oe=64DE23BD&_nc_sid=17eaee",
                    "username": "afi_luthfia"
                },
                "likes_count": 0
            }
        ]
    },
    {
        "id": 18003297067526760,
        "created_at": 1670493585,
        "text": "\ud83d\udd25\ud83d\udd25\ud83d\udd25",
        "owner": {
            "id": "6140564852",
            "is_verified": false,
            "profile_pic_url": "https://scontent-sin6-2.cdninstagram.com/v/t51.2885-19/360062408_1004588910578741_3837303722277580051_n.jpg?stp=dst-jpg_s150x150&_nc_ht=scontent-sin6-2.cdninstagram.com&_nc_cat=105&_nc_ohc=ReaAWwFdUDEAX-QYswq&edm=AMrZAGUBAAAA&ccb=7-5&oh=00_AfAQvGgCuuCDIPhCpXU47e215tVCofaxpb9nkgzKesRfjg&oe=64DE3817&_nc_sid=17eaee",
            "username": "myvrnc"
        },
        "likes_count": 1,
        "answers": []
    }
]